feeluown_bilibili-0.5.4.dist-info/licenses/LICENSE.txt
fuo_bilibili/__init__.py
fuo_bilibili/const.py
fuo_bilibili/danmaku2ass.py
fuo_bilibili/login.py
fuo_bilibili/model.py
fuo_bilibili/page_home.py
fuo_bilibili/page_ranking.py
fuo_bilibili/provider.py
fuo_bilibili/qt_compat.py
fuo_bilibili/ui.py
fuo_bilibili/util.py
fuo_bilibili/api/__init__.py
fuo_bilibili/api/audio.py
fuo_bilibili/api/base.py
fuo_bilibili/api/compat.py
fuo_bilibili/api/history.py
fuo_bilibili/api/live.py
fuo_bilibili/api/login.py
fuo_bilibili/api/media.py
fuo_bilibili/api/playlist.py
fuo_bilibili/api/user.py
fuo_bilibili/api/video.py
fuo_bilibili/api/wbi.py
fuo_bilibili/api/schema/__init__.py
fuo_bilibili/api/schema/enums.py
fuo_bilibili/api/schema/requests.py
fuo_bilibili/api/schema/responses.py
fuo_bilibili/assets/icon.svg
fuo_bilibili/geetest/__init__.py
fuo_bilibili/geetest/index.html
fuo_bilibili/geetest/server.py
feeluown_bilibili-0.5.4.dist-info/METADATA
feeluown_bilibili-0.5.4.dist-info/WHEEL
feeluown_bilibili-0.5.4.dist-info/entry_points.txt
feeluown_bilibili-0.5.4.dist-info/top_level.txt
feeluown_bilibili-0.5.4.dist-info/RECORD
