Metadata-Version: 2.4
Name: feeluown-bilibili
Version: 0.5.4
Summary: Bilibili provider for FeelUOwn player.
Home-page: https://github.com/feeluown/feeluown-bilibili
Author: Bruce Zhang
Requires-Python: >=3.10,<4.0
License-File: LICENSE.txt
Requires-Dist: beautifulsoup4
Requires-Dist: cachetools
Requires-Dist: feeluown>=4.1.8
Requires-Dist: pycryptodome
Dynamic: author
Dynamic: home-page
Dynamic: license-file
Dynamic: requires-dist
Dynamic: requires-python
Dynamic: summary
